setup.py
dm/__init__.py
dm.zodb.asynchronous.egg-info/PKG-INFO
dm.zodb.asynchronous.egg-info/SOURCES.txt
dm.zodb.asynchronous.egg-info/dependency_links.txt
dm.zodb.asynchronous.egg-info/namespace_packages.txt
dm.zodb.asynchronous.egg-info/not-zip-safe
dm.zodb.asynchronous.egg-info/requires.txt
dm.zodb.asynchronous.egg-info/top_level.txt
dm/zodb/__init__.py
dm/zodb/asynchronous/LICENSE.txt
dm/zodb/asynchronous/README.txt
dm/zodb/asynchronous/VERSION.txt
dm/zodb/asynchronous/__init__.py
dm/zodb/asynchronous/context.py
dm/zodb/asynchronous/pycompat.py
dm/zodb/asynchronous/scheduler.py
dm/zodb/asynchronous/transactional.py
dm/zodb/asynchronous/zope2.py
dm/zodb/asynchronous/tests/__init__.py
dm/zodb/asynchronous/tests/test_scheduler.py
dm/zodb/asynchronous/tests/test_transactional.py
dm/zodb/asynchronous/tests/test_zope2.py