Metadata-Version: 1.1
Name: dm.zodb.asynchronous
Version: 2.2
Summary: Utilities to implement asynchronous operations accessing the ZODB
Home-page: https://pypi.org/project/dm.zodb.asynchronous/
Author: Dieter Maurer
Author-email: dieter@handshake.de
License: BSD
Keywords: ZODB thread asynchronous utilities
Platform: UNKNOWN
Classifier: Development Status :: 5 - Production/Stable
Classifier: Intended Audience :: Developers
Classifier: License :: OSI Approved :: BSD License
Classifier: Framework :: Zope2
Classifier: Framework :: Zope :: 4
Classifier: Framework :: ZODB
Classifier: Operating System :: OS Independent
Classifier: Programming Language :: Python
Classifier: Programming Language :: Python :: 2.7
Classifier: Programming Language :: Python :: 3
Classifier: Topic :: Utilities
